VoiceHelper/CommandsHandler.py
VoiceHelper/Exceptions.py
VoiceHelper/NueroNetworks.py
VoiceHelper/Unitsdata.py
VoiceHelper/VoiceHelper.py
VoiceHelper/__init__.py
VoiceHelper/__main__.py
VoiceHelper/models/srec/ru-rus_small/README
VoiceHelper/models/srec/ru-rus_small/am/final.mdl
VoiceHelper/models/srec/ru-rus_small/conf/mfcc.conf
VoiceHelper/models/srec/ru-rus_small/conf/model.conf
VoiceHelper/models/srec/ru-rus_small/graph/Gr.fst
VoiceHelper/models/srec/ru-rus_small/graph/HCLr.fst
VoiceHelper/models/srec/ru-rus_small/graph/disambig_tid.int
VoiceHelper/models/srec/ru-rus_small/graph/phones/word_boundary.int
VoiceHelper/models/srec/ru-rus_small/ivector/final.dubm
VoiceHelper/models/srec/ru-rus_small/ivector/final.ie
VoiceHelper/models/srec/ru-rus_small/ivector/final.mat
VoiceHelper/models/srec/ru-rus_small/ivector/global_cmvn.stats
VoiceHelper/models/srec/ru-rus_small/ivector/online_cmvn.conf
VoiceHelper/models/srec/ru-rus_small/ivector/splice.conf
VoiceHelper/models/ssynth/ru-ru_v3.pt
voicehelper.py-0.1.7.dist-info/LICENSE
voicehelper.py-0.1.7.dist-info/METADATA
voicehelper.py-0.1.7.dist-info/WHEEL
voicehelper.py-0.1.7.dist-info/top_level.txt
voicehelper.py-0.1.7.dist-info/RECORD
