Metadata-Version: 2.1
Name: voicehelper.py
Version: 0.1.7
Summary: These are two neural networks connected by the same module. One for recognition, the other for voice generation.
Home-page: https://github.com/romanin-rf/voicehelper.py
Author: Romanin
Author-email: semina054@gmail.com
License: MIT
Platform: UNKNOWN
Requires-Python: >=3.9
License-File: LICENSE
Requires-Dist: numpy
Requires-Dist: sounddevice
Requires-Dist: pysoundfile
Requires-Dist: requests
Requires-Dist: wget
Requires-Dist: vosk
Requires-Dist: silero
Requires-Dist: vbml
Requires-Dist: rich
